setup.cfg
setup.py
pyGachi/__init__.py
pyGachi/gosBel_3_bileta_net.py
pyGachi/oop1_b_3.py
pyGachi/oop2_b_11.py
pyGachi/oop3_bileta_net.py
pyGachi/oop4_bileta_net.py
pyGachi/oop5_b_14.py
pyGachi/oop6_b_21.py
pyGachi/prog10_b_22.py
pyGachi/prog11_b_10.py
pyGachi/prog12_b_25.py
pyGachi/prog13_b_30.py
pyGachi/prog14_b_24.py
pyGachi/prog15_b_27.py
pyGachi/prog16_bileta_net.py
pyGachi/prog17_bileta_net.py
pyGachi/prog18_bileta_net.py
pyGachi/prog19_bileta_net.py
pyGachi/prog1_b_7.py
pyGachi/prog20_bileta_net.py
pyGachi/prog2_b_28.py
pyGachi/prog3_bileta_net.py
pyGachi/prog4_b_17.py
pyGachi/prog5_b_4.py
pyGachi/prog6_b_29.py
pyGachi/prog7_b_1.py
pyGachi/prog8_b_20.py
pyGachi/prog9_b_13.py
pyGachi/siaod1_b_5.py
pyGachi/siaod2_b_19,26.py
pyGachi.egg-info/PKG-INFO
pyGachi.egg-info/SOURCES.txt
pyGachi.egg-info/dependency_links.txt
pyGachi.egg-info/requires.txt
pyGachi.egg-info/top_level.txt
pyGachi.egg-info/Files/FAQ.docx
pyGachi.egg-info/Files/PascalABCNET.chm
pyGachi.egg-info/Files/PascalABCNET.chw
pyGachi.egg-info/Files/license.docx
pyGachi.egg-info/Files/tckts(1).docx
pyGachi.egg-info/Files/~$FAQ.docx
pyGachi.egg-info/Files/bd/Z_1_b_2.accdb
pyGachi.egg-info/Files/bd/Z_2_b_8.accdb
pyGachi.egg-info/Files/bd/Z_3_bileta_net.accdb
pyGachi.egg-info/Files/bd/Z_4_b_26.accdb
pyGachi.egg-info/Files/bd/Z_5_bileta_net.accdb
pyGachi.egg-info/Files/bd/Z_6_b_18.accdb
pyGachi.egg-info/Files/bd/Z_7_b_16.accdb
pyGachi.egg-info/Files/bd/Z_8_bileta_net.accdb
pyGachi.egg-info/Files/bd/Z_9_b_23.accdb
pyGachi.egg-info/Files/proga/book1.txt
pyGachi.egg-info/Files/proga/grades.txt
pyGachi.egg-info/Files/unity/AddForceGuide.txt
pyGachi.egg-info/Files/unity/AddForce_b_19.unitypackage
pyGachi.egg-info/Files/unity/Ragdoll_b_6.unitypackage
pyGachi.egg-info/Files/unity/ShootingGuide.txt
pyGachi.egg-info/Files/unity/ShootingPackage_b_9.unitypackage
pyGachi.egg-info/Files/unity/SoundBox_b_15.unitypackage
pyGachi.egg-info/Files/unity/WaterGuide.txt
pyGachi.egg-info/Files/unity/collisions_b_9.unitypackage
pyGachi.egg-info/Files/unity/water_b_12.unitypackage