Metadata-Version: 2.1
Name: pyGachi
Version: 1.6
Summary: Brat ne trogai, eto tibe ne nado
Home-page: https://github.com/DANILYH/pyGachi
Download-URL: https://github.com/DANILYH/pyGachi/archive/v1.6.zip
Author: GachiParty
Author-email: fetom30268@cutefier.com
License: Apache License, Version 2.0, see LICENSE file
Classifier: License :: OSI Approved :: Apache Software License
Classifier: Operating System :: OS Independent
Classifier: Intended Audience :: End Users/Desktop
Classifier: Intended Audience :: Developers
Classifier: Programming Language :: Python
Classifier: Programming Language :: Python :: 3
Classifier: Programming Language :: Python :: 3.8
Classifier: Programming Language :: Python :: 3.9
Classifier: Programming Language :: Python :: 3.10
Classifier: Programming Language :: Python :: 3.11
Classifier: Programming Language :: Python :: 3.12
Classifier: Programming Language :: Python :: Implementation :: PyPy
Classifier: Programming Language :: Python :: Implementation :: CPython
